prairiebuild/__init__.py
prairiebuild/__main__.py
prairiebuild-0.1.0.dist-info/METADATA
prairiebuild-0.1.0.dist-info/WHEEL
prairiebuild-0.1.0.dist-info/entry_points.txt
prairiebuild-0.1.0.dist-info/top_level.txt
prairiebuild-0.1.0.dist-info/RECORD
