Metadata-Version: 2.1
Name: prairiebuild
Version: 0.1.0
Summary: Command-line tool for building PrairieLearn questions
Author-email: Benjamin Darnell <ben@bdarnell.com>
Requires-Python: >=3.7
Requires-Dist: PyYAML >=6.0
